fridump3/__main__.py
fridump3/console.py
fridump3/src/dumper.py
fridump3/src/utils.py
fridump3-1.0.0.dist-info/METADATA
fridump3-1.0.0.dist-info/WHEEL
fridump3-1.0.0.dist-info/entry_points.txt
fridump3-1.0.0.dist-info/RECORD
