Metadata-Version: 2.3
Name: fridump3
Version: 1.0.0
Summary: A universal memory dumper using Frida for Python 3.
License: GPL-3.0-or-later
Requires-Python: >=3.7,<4.0
Classifier: License :: OSI Approved :: GNU General Public License v3 or later (GPLv3+)
Classifier: Programming Language :: Python :: 3
Classifier: Programming Language :: Python :: 3.7
Classifier: Programming Language :: Python :: 3.8
Classifier: Programming Language :: Python :: 3.9
Classifier: Programming Language :: Python :: 3.10
Classifier: Programming Language :: Python :: 3.11
Classifier: Programming Language :: Python :: 3.12
Classifier: Programming Language :: Python :: 3.13
Requires-Dist: frida
Requires-Dist: loguru
Project-URL: Repository, https://github.com/rootbsd/fridump3
